Tensorflow101Sjchoi86/README.md
Tensorflow101Sjchoi86/__init__.py
Tensorflow101Sjchoi86/__main__.py
Tensorflow101Sjchoi86/file.epub
Tensorflow101Sjchoi86/index.html
Tensorflow101Sjchoi86/css/__init__.py
Tensorflow101Sjchoi86/css/annotations.css
Tensorflow101Sjchoi86/css/main.css
Tensorflow101Sjchoi86/css/normalize.css
Tensorflow101Sjchoi86/css/popup.css
Tensorflow101Sjchoi86/font/__init__.py
Tensorflow101Sjchoi86/font/fontello.eot
Tensorflow101Sjchoi86/font/fontello.svg
Tensorflow101Sjchoi86/font/fontello.ttf
Tensorflow101Sjchoi86/font/fontello.woff
Tensorflow101Sjchoi86/img/__init__.py
Tensorflow101Sjchoi86/img/annotator-glyph-sprite.png
Tensorflow101Sjchoi86/img/annotator-icon-sprite.png
Tensorflow101Sjchoi86/img/apple-touch-icon.png
Tensorflow101Sjchoi86/img/cancelfullscreen.png
Tensorflow101Sjchoi86/img/close.png
Tensorflow101Sjchoi86/img/fullscreen.png
Tensorflow101Sjchoi86/img/loader.gif
Tensorflow101Sjchoi86/img/menu-icon.png
Tensorflow101Sjchoi86/img/save.png
Tensorflow101Sjchoi86/img/saved.png
Tensorflow101Sjchoi86/img/settings-s.png
Tensorflow101Sjchoi86/img/settings.png
Tensorflow101Sjchoi86/img/star.png
Tensorflow101Sjchoi86/js/__init__.py
Tensorflow101Sjchoi86/js/epub.js
Tensorflow101Sjchoi86/js/epub.min.js
Tensorflow101Sjchoi86/js/epub.min.map
Tensorflow101Sjchoi86/js/hooks.min.js
Tensorflow101Sjchoi86/js/hooks.min.map
Tensorflow101Sjchoi86/js/reader.js
Tensorflow101Sjchoi86/js/reader.js.map
Tensorflow101Sjchoi86/js/reader.min.js
Tensorflow101Sjchoi86/js/reader.min.map
Tensorflow101Sjchoi86/js/hooks/__init__.py
Tensorflow101Sjchoi86/js/hooks/extensions/__init__.py
Tensorflow101Sjchoi86/js/hooks/extensions/highlight.js
Tensorflow101Sjchoi86/js/libs/__init__.py
Tensorflow101Sjchoi86/js/libs/jquery.min.js
Tensorflow101Sjchoi86/js/libs/localforage.min.js
Tensorflow101Sjchoi86/js/libs/screenfull.js
Tensorflow101Sjchoi86/js/libs/screenfull.min.js
Tensorflow101Sjchoi86/js/libs/zip.min.js
Tensorflow101Sjchoi86/js/plugins/__init__.py
tensorflow_101_sjchoi86-2024.3.3.0.dist-info/METADATA
tensorflow_101_sjchoi86-2024.3.3.0.dist-info/WHEEL
tensorflow_101_sjchoi86-2024.3.3.0.dist-info/entry_points.txt
tensorflow_101_sjchoi86-2024.3.3.0.dist-info/top_level.txt
tensorflow_101_sjchoi86-2024.3.3.0.dist-info/RECORD
